text_to_audio/__init__.py
text_to_audio/cli.py
text_to_audio/patches.py
text_to_audio/tts.py
text_to_audio-1.0.1.dist-info/METADATA
text_to_audio-1.0.1.dist-info/WHEEL
text_to_audio-1.0.1.dist-info/entry_points.txt
text_to_audio-1.0.1.dist-info/licenses/LICENSE
text_to_audio-1.0.1.dist-info/RECORD
