Metadata-Version: 2.4
Name: text-to-audio
Version: 1.0.1
Summary: Text-to-audio generator using Chatterbox TTS with automatic long text handling
Project-URL: Homepage, https://github.com/Kotivskyi/text-to-audio
Project-URL: Repository, https://github.com/Kotivskyi/text-to-audio
Project-URL: Issues, https://github.com/Kotivskyi/text-to-audio/issues
License-Expression: MIT
License-File: LICENSE
Keywords: audio,chatterbox,text-to-speech,tts,voice-cloning
Classifier: Development Status :: 4 - Beta
Classifier: Intended Audience :: Developers
Classifier: License :: OSI Approved :: MIT License
Classifier: Programming Language :: Python :: 3
Classifier: Programming Language :: Python :: 3.11
Classifier: Programming Language :: Python :: 3.12
Classifier: Topic :: Multimedia :: Sound/Audio :: Speech
Requires-Python: >=3.11
Requires-Dist: chatterbox-tts
Requires-Dist: ml-dtypes>=0.5.0
Requires-Dist: peft
Requires-Dist: torch
Requires-Dist: torchaudio
